{
    "FB": {
        "Open": 223.5,
        "High": 230.33,
        "Low": 223.19,
        "Close": 229.32,
        "Volume": 23558879.0,
        "Dividends": 0.0,
        "Stock Splits": 0.0
    },
    "HAL": {
        "Open": 11.43,
        "High": 11.9,
        "Low": 11.36,
        "Close": 11.86,
        "Volume": 12208257.0,
        "Dividends": 0.0,
        "Stock Splits": 0.0
    },
    "TWTR": {
        "Open": 30.5,
        "High": 31.65,
        "Low": 30.45,
        "Close": 31.64,
        "Volume": 10873743.0,
        "Dividends": 0.0,
        "Stock Splits": 0.0
    },
    "INTC": {
        "Open": 61.16,
        "High": 63.48,
        "Low": 61.02,
        "Close": 63.46,
        "Volume": 11066573.0,
        "Dividends": 0.0,
        "Stock Splits": 0.0
    },
    "NOK": {
        "Open": 3.74,
        "High": 3.83,
        "Low": 3.73,
        "Close": 3.81,
        "Volume": 10557062.0,
        "Dividends": 0.0,
        "Stock Splits": 0.0
    },
    "VALE": {
        "Open": 9.35,
        "High": 9.45,
        "Low": 9.27,
        "Close": 9.35,
        "Volume": 10404277.0,
        "Dividends": 0.0,
        "Stock Splits": 0.0
    },
    "BABA": {
        "Open": 220.0,
        "High": 221.16,
        "Low": 218.94,
        "Close": 220.85,
        "Volume": 7429795.0,
        "Dividends": 0.0,
        "Stock Splits": 0.0
    },
    "ZNGA": {
        "Open": 8.14,
        "High": 8.3,
        "Low": 8.12,
        "Close": 8.19,
        "Volume": 6774311.0,
        "Dividends": 0.0,
        "Stock Splits": 0.0
    },
    "CSCO": {
        "Open": 45.05,
        "High": 45.78,
        "Low": 45.04,
        "Close": 45.71,
        "Volume": 6558606.0,
        "Dividends": 0.0,
        "Stock Splits": 0.0
    },
    "MRVL": {
        "Open": 28.02,
        "High": 29.17,
        "Low": 27.94,
        "Close": 29.03,
        "Volume": 6602765.0,
        "Dividends": 0.0,
        "Stock Splits": 0.0
    },
    "EQNR": {
        "Open": 15.0,
        "High": 15.2,
        "Low": 14.93,
        "Close": 15.05,
        "Volume": 5588201.0,
        "Dividends": 0.0,
        "Stock Splits": 0.0
    },
    "ERI": {
        "Open": 30.55,
        "High": 32.0,
        "Low": 29.79,
        "Close": 31.58,
        "Volume": 5647245.0,
        "Dividends": 0.0,
        "Stock Splits": 0.0
    },
    "CARR": {
        "Open": 18.16,
        "High": 19.05,
        "Low": 18.16,
        "Close": 18.94,
        "Volume": 5537213.0,
        "Dividends": 0.0,
        "Stock Splits": 0.0
    },
    "PENN": {
        "Open": 25.62,
        "High": 27.3,
        "Low": 25.02,
        "Close": 25.83,
        "Volume": 18995752.0,
        "Dividends": 0.0,
        "Stock Splits": 0.0
    }
}